LICENSE
README.md
setup.cfg
setup.py
pipdu_sdk/__init__.py
pipdu_sdk/pipdu.py
pipdu_sdk.egg-info/PKG-INFO
pipdu_sdk.egg-info/SOURCES.txt
pipdu_sdk.egg-info/dependency_links.txt
pipdu_sdk.egg-info/requires.txt
pipdu_sdk.egg-info/top_level.txt
pipdu_sdk/config/__init__.py
pipdu_sdk/config/v1_0_0.py