Metadata-Version: 2.1
Name: pipdu-sdk
Version: 1.0.0.dev4076314134
Summary: PiPDU python SDK
Home-page: https://gitlab.com/mirceanton/piPDU/-/tree/main/utils/python_sdk
Author: Mircea-Pavel Anton
Author-email: contact@mirceanton.com
License: MIT
Project-URL: Bug Tracker, https://gitlab.com/mirceanton/piPDU/-/issues
Keywords: pypi,pipdu,mirceanton
Platform: UNKNOWN
License-File: LICENSE
